HiveWebCrawler/Crawler.py
HiveWebCrawler/__init__.py
HiveWebCrawler/instaCrawl.py
HiveWebCrawler-0.1.6.dist-info/LICENSE
HiveWebCrawler-0.1.6.dist-info/METADATA
HiveWebCrawler-0.1.6.dist-info/WHEEL
HiveWebCrawler-0.1.6.dist-info/top_level.txt
HiveWebCrawler-0.1.6.dist-info/RECORD
