Metadata-Version: 2.1
Name: HiveWebCrawler
Version: 0.1.6
Summary: Python 3.x Web Crawler, Images, Urls, Emails, Phone numbers
Home-page: https://github.com/MehmetYukselSekeroglu/HiveWebCrawler
Author: MehmetYukselSekeroglu
Author-email: dijital_evren@protonmail.com
Project-URL: Bug Reports, https://github.com/MehmetYukselSekeroglu/HiveWebCrawler/issues
Project-URL: Source Code, https://github.com/MehmetYukselSekeroglu/HiveWebCrawler
Keywords: PyPi,Web Crawler,Web Image Crawler,Web URL Crawler,Web Email Crawler,Web Phone Number Crawler
Requires-Python: >=3.8
License-File: LICENSE
Requires-Dist: requests
Requires-Dist: beautifulsoup4
Requires-Dist: urllib
